{
  "variants":{
    "meta=0":{"model":"rtm:moving_machine"},
    "meta=1":{"model":"rtm:vehicle_generator"},
    "meta=2":{"model":"rtm:moving_machine"},
    "meta=3":{"model":"rtm:moving_machine"},
    "meta=4":{"model":"rtm:moving_machine"},
    "meta=5":{"model":"rtm:moving_machine"},
    "meta=6":{"model":"rtm:moving_machine"},
    "meta=7":{"model":"rtm:moving_machine"},
    "meta=8":{"model":"rtm:moving_machine"},
    "meta=9":{"model":"rtm:moving_machine"},
    "meta=10":{"model":"rtm:moving_machine"},
    "meta=11":{"model":"rtm:moving_machine"},
    "meta=12":{"model":"rtm:moving_machine"},
    "meta=13":{"model":"rtm:moving_machine"},
    "meta=14":{"model":"rtm:moving_machine"},
    "meta=15":{"model":"rtm:moving_machine"}
  }
}